topsis_haryiank_102303088/__init__.py
topsis_haryiank_102303088/topsis.py
topsis_haryiank_102303088-1.0.2.dist-info/licenses/LICENSE
topsis_haryiank_102303088-1.0.2.dist-info/METADATA
topsis_haryiank_102303088-1.0.2.dist-info/WHEEL
topsis_haryiank_102303088-1.0.2.dist-info/entry_points.txt
topsis_haryiank_102303088-1.0.2.dist-info/top_level.txt
topsis_haryiank_102303088-1.0.2.dist-info/RECORD
