Metadata-Version: 2.4
Name: Topsis-Haryiank-102303088
Version: 1.0.2
Summary: A Python package for TOPSIS (Technique for Order of Preference by Similarity to Ideal Solution) analysis
Home-page: https://github.com/HaryiankKumra/TOPSIS
Author: Haryiank Kumra
Author-email: haryiank@gmail.com
Classifier: Programming Language :: Python :: 3
Classifier: License :: OSI Approved :: MIT License
Classifier: Operating System :: OS Independent
Requires-Python: >=3.6
License-File: LICENSE
Requires-Dist: pandas>=1.0.0
Requires-Dist: numpy>=1.18.0
Dynamic: author
Dynamic: author-email
Dynamic: classifier
Dynamic: description
Dynamic: description-content-type
Dynamic: home-page
Dynamic: license-file
Dynamic: requires-dist
Dynamic: requires-python
Dynamic: summary
